json_merge_tree/__init__.py
json_merge_tree/json_objects.py
json_merge_tree-0.7.3.dist-info/METADATA
json_merge_tree-0.7.3.dist-info/WHEEL
json_merge_tree-0.7.3.dist-info/RECORD
