Metadata-Version: 2.3
Name: json-merge-tree
Version: 0.7.3
Summary: JSON Merge Tree (built on top of json-multi-merge) merges JSON objects in a hierarchy, allowing customization of how objects are merged.
License: MIT
Author: Marcy Buccellato
Author-email: mbuccellato@hearst.com
Requires-Python: >=3.9,<4.0
Classifier: License :: OSI Approved :: MIT License
Classifier: Programming Language :: Python :: 3
Classifier: Programming Language :: Python :: 3.9
Classifier: Programming Language :: Python :: 3.10
Classifier: Programming Language :: Python :: 3.11
Classifier: Programming Language :: Python :: 3.12
Classifier: Programming Language :: Python :: 3.13
Requires-Dist: json-multi-merge (>=0.3.1)
Requires-Dist: sqlalchemy (>=2.0.0)
